adrubix/__init__.py
adrubix/_version.py
adrubix/rubixheatmap.py
tests/__init__.py
tests/conftest.py
tests/test_adrubix.py
adrubix-0.1.66.dist-info/LICENSE
adrubix-0.1.66.dist-info/METADATA
adrubix-0.1.66.dist-info/WHEEL
adrubix-0.1.66.dist-info/top_level.txt
adrubix-0.1.66.dist-info/RECORD
